kaygraph/KayFlow.txt
kaygraph/__init__.py
kaygraph/cli.py
kaygraph/composition.py
kaygraph/interactive.py
kaygraph/new-updates-agent-loop.txt
kaygraph/persistence.py
kaygraph/workflow_loader.py
kaygraph/.claude/settings.local.json
kaygraph/agent/__init__.py
kaygraph/agent/anthropic_patterns.py
kaygraph/agent/nodes.py
kaygraph/agent/patterns.py
kaygraph/agent/tools.py
kaygraph/declarative/__init__.py
kaygraph/declarative/serializer.py
kaygraph/declarative/visual_converter.py
kaygraph-0.3.2.dist-info/METADATA
kaygraph-0.3.2.dist-info/WHEEL
kaygraph-0.3.2.dist-info/licenses/LICENSE
kaygraph-0.3.2.dist-info/RECORD
