Metadata-Version: 2.4
Name: kaygraph
Version: 0.3.2
Summary: A context-graph framework for building production-ready AI applications.
Project-URL: Homepage, https://github.com/KayOS-AI/KayGraph
Project-URL: Issues, https://github.com/KayOS-AI/KayGraph/issues
Project-URL: Documentation, https://github.com/KayOS-AI/KayGraph
Author-email: KayOS Team <team@kayos.ai>
License: AGPL-3.0
License-File: LICENSE
Keywords: agentic,ai,context,graphs,llm,workflow
Classifier: Development Status :: 3 - Alpha
Classifier: Intended Audience :: Developers
Classifier: License :: OSI Approved :: GNU Affero General Public License v3
Classifier: Programming Language :: Python :: 3
Classifier: Programming Language :: Python :: 3.11
Classifier: Programming Language :: Python :: 3.12
Classifier: Programming Language :: Python :: 3.13
Classifier: Topic :: Scientific/Engineering :: Artificial Intelligence
Classifier: Topic :: Software Development :: Libraries :: Python Modules
Requires-Python: >=3.11
Provides-Extra: dev
Requires-Dist: pytest-asyncio>=0.21.0; extra == 'dev'
Requires-Dist: pytest-cov>=4.0.0; extra == 'dev'
Requires-Dist: pytest>=7.0.0; extra == 'dev'
Requires-Dist: ruff>=0.1.0; extra == 'dev'
